{
      
    "jointFile"     : "head_joint.ma",    
    "layoutFile"    : "head_template.ma",    
    "jointNodeList" : ["neck__SIDE__jnt", "head__SIDE__jnt", "headEnd__SIDE__jnt" ],
    "layoutNodeList": ["root", "headEnd_pos", "constMe_to_parent", "headEnd_zro", "hdl_grp", "neck_zro", "result_neck", "head_up", "head_jo", "neck_jo", "parent", "rig_grp", "neck_aim", "result_head", "neck_aim_zro", "neck_pos", "head_pos", "head_up_zro", "neck_rot", "result_headEnd", "head_back_zro", "const_grp", "result_grp", "head_back", "calc_jointOrient_grp" ],
    "rootJnt"       : ["neck__SIDE__jnt"],
    
    "snap_layToJnt":[
	    	{"hdl":"root", 			"jnt":"head__SIDE__jnt", 		"type":"parent", "offset":null},
	    	{"hdl":"head_up_zro", 	"jnt":"headEnd__SIDE__jnt", 	"type":"parent", "offset":null},
	    	{"hdl":"head_back_zro", "jnt":"head__SIDE__jnt", 		"type":"parent", "offset":null},
	    	{"hdl":"headEnd_zro", 	"jnt":"headEnd__SIDE__jnt", 	"type":"parent", "offset":null},
	    	{"hdl":"neck_aim_zro", 	"jnt":"neck__SIDE__jnt", 		"type":"parent", "offset":null},
	    	{"hdl":"neck_zro", 		"jnt":"neck__SIDE__jnt", 		"type":"parent", "offset":null},
	    	{"hdl":"head_up", 		"jnt":"headEnd__SIDE__jnt", 	"type":"parent", "offset":[2,0,0]},
	    	{"hdl":"head_back", 	"jnt":"head__SIDE__jnt", 		"type":"parent", "offset":[0,5,0]},
	    	{"hdl":"neck_aim", 		"jnt":"head__SIDE__jnt", 		"type":"parent", "offset":[-2,0,0]}
    	],
    
    "const_JntToLay":[
            {"outputNode":"result_neck",	"target":"neck__SIDE__jnt"},
        	{"outputNode":"result_head",	"target":"head__SIDE__jnt"},
        	{"outputNode":"result_headEnd", "target":"headEnd__SIDE__jnt"}
    	]
}